soco_cli/__init__.py
soco_cli/__main__.py
soco_cli/action_processor.py
soco_cli/alarms.py
soco_cli/aliases.py
soco_cli/api.py
soco_cli/check_for_update.py
soco_cli/cmd_parser.py
soco_cli/http_api.py
soco_cli/interactive.py
soco_cli/keystroke_capture.py
soco_cli/m3u_parser.py
soco_cli/match_speaker_names.py
soco_cli/play_local_file.py
soco_cli/play_local_file_lists.py
soco_cli/sonos.py
soco_cli/sonos_discover.py
soco_cli/speaker_info.py
soco_cli/speakers.py
soco_cli/track_follow.py
soco_cli/utils.py
soco_cli/wait_actions.py
soco_cli-0.4.82.dist-info/licenses/LICENSE
soco_cli-0.4.82.dist-info/METADATA
soco_cli-0.4.82.dist-info/WHEEL
soco_cli-0.4.82.dist-info/entry_points.txt
soco_cli-0.4.82.dist-info/top_level.txt
soco_cli-0.4.82.dist-info/RECORD
